flask_more_smorest/__init__.py
flask_more_smorest/crud/__init__.py
flask_more_smorest/crud/blueprint_operationid.py
flask_more_smorest/crud/crud_blueprint.py
flask_more_smorest/crud/pagination.py
flask_more_smorest/crud/query_filtering.py
flask_more_smorest/error/__init__.py
flask_more_smorest/error/error_handlers.py
flask_more_smorest/error/exceptions.py
flask_more_smorest/perms/__init__.py
flask_more_smorest/perms/api.py
flask_more_smorest/perms/base_perms_model.py
flask_more_smorest/perms/jwt.py
flask_more_smorest/perms/model_mixins.py
flask_more_smorest/perms/models/__init__.py
flask_more_smorest/perms/models/abstract_role.py
flask_more_smorest/perms/models/abstract_setting.py
flask_more_smorest/perms/models/abstract_token.py
flask_more_smorest/perms/models/abstract_user.py
flask_more_smorest/perms/models/base_roles.py
flask_more_smorest/perms/models/defaults.py
flask_more_smorest/perms/models/role.py
flask_more_smorest/perms/models/setting.py
flask_more_smorest/perms/models/token.py
flask_more_smorest/perms/models/user.py
flask_more_smorest/perms/perms_blueprint.py
flask_more_smorest/perms/user_blueprint.py
flask_more_smorest/perms/user_context.py
flask_more_smorest/perms/user_registry.py
flask_more_smorest/perms/user_schemas.py
flask_more_smorest/protocols.py
flask_more_smorest/py.typed
flask_more_smorest/sqla/__init__.py
flask_more_smorest/sqla/base_model.py
flask_more_smorest/sqla/database.py
flask_more_smorest/sqla/migrations.py
flask_more_smorest/sqla/schema.py
flask_more_smorest/testing.py
flask_more_smorest/utils.py
flask_more_smorest-0.10.4.dist-info/METADATA
flask_more_smorest-0.10.4.dist-info/WHEEL
flask_more_smorest-0.10.4.dist-info/licenses/LICENSE
flask_more_smorest-0.10.4.dist-info/RECORD
