Metadata-Version: 2.4
Name: flask-more-smorest
Version: 0.10.4
Summary: Enhanced Flask-Smorest blueprints with automatic CRUD operations
License-File: LICENSE
Keywords: flask,api,rest,crud,smorest,blueprint,sqlalchemy
Author: Dave
Author-email: david@qualisero.com
Maintainer: Dave
Maintainer-email: david@qualisero.com
Requires-Python: >=3.11,<4.0
Classifier: Development Status :: 4 - Beta
Classifier: Framework :: Flask
Classifier: Intended Audience :: Developers
Classifier: License :: OSI Approved :: MIT License
Classifier: Operating System :: OS Independent
Classifier: Programming Language :: Python :: 3
Classifier: Programming Language :: Python :: 3.11
Classifier: Programming Language :: Python :: 3.12
Classifier: Programming Language :: Python :: 3.13
Classifier: Programming Language :: Python :: 3.14
Classifier: Topic :: Database :: Database Engines/Servers
Classifier: Topic :: Internet :: WWW/HTTP :: HTTP Servers
Classifier: Topic :: Software Development :: Libraries :: Python Modules
Requires-Dist: alembic (>=1.13.0,<2.0.0)
Requires-Dist: bcrypt (>=4.1.0,<5.0.0)
Requires-Dist: flask (>=3.0.0,<4.0.0)
Requires-Dist: flask-jwt-extended (>=4.6.0,<5.0.0)
Requires-Dist: flask-smorest
Requires-Dist: flask-sqlalchemy (>=3.1.1,<4.0.0)
Requires-Dist: marshmallow (>=3.20.0,<4.0.0)
Requires-Dist: marshmallow-sqlalchemy (>=1.4.2,<2.0.0)
Requires-Dist: sqlalchemy (>=2.0.25,<3.0.0)
Requires-Dist: werkzeug (>=3.0.0,<4.0.0)
Project-URL: Documentation, https://github.com/qualisero/flask-more-smorest#readme
Project-URL: Homepage, https://github.com/qualisero/flask-more-smorest
Project-URL: Repository, https://github.com/qualisero/flask-more-smorest
